mylib_047/__init__.py
mylib_047-0.1.dist-info/LICENSE.txt
mylib_047-0.1.dist-info/METADATA
mylib_047-0.1.dist-info/WHEEL
mylib_047-0.1.dist-info/top_level.txt
mylib_047-0.1.dist-info/RECORD
